{
  "source": "Canton protobuf trees from published release bundles",
  "release_url_template": "https://www.canton.io/releases/canton-open-source-{version}.tar.gz",
  "bundle_proto_dir": "protobuf",
  "repo": {
    "remote": "https://github.com/DACH-NY/canton.git",
    "web_url": "https://github.com/DACH-NY/canton"
  },
  "min_version": "3.2.0",
  "excluded_versions": ["3.4.1"],
  "versions": [
    "3.4.0",
    "3.4.2",
    "3.4.3",
    "3.4.4",
    "3.4.5",
    "3.4.6",
    "3.4.7",
    "3.4.8",
    "3.4.9",
    "3.4.10",
    "3.4.11"
  ],
  "metadata_path": "config/x2mdx/protobuf-history/metadata.json"
}
